idea/__init__.py
idea/code_old.py
idea/del.py
idea/get_code.py
puffidea-0.1.3.dist-info/LICENSE
puffidea-0.1.3.dist-info/METADATA
puffidea-0.1.3.dist-info/WHEEL
puffidea-0.1.3.dist-info/entry_points.txt
puffidea-0.1.3.dist-info/top_level.txt
puffidea-0.1.3.dist-info/RECORD
