Metadata-Version: 2.1
Name: puffidea
Version: 0.1.3
Summary: 获取Jetbrains激活码
Home-page: https://github.com/PeterPuffer/puffidea
Author: puff
Author-email: angrypuff333@gmail.com
License: UNKNOWN
Platform: UNKNOWN
Classifier: Programming Language :: Python :: 2
Classifier: License :: OSI Approved :: MIT License
Classifier: Operating System :: OS Independent
Requires-Dist: requests
Requires-Dist: pyperclip
